tests/logic/__init__.py
tests/logic/test_game_state.py
tests/logic/test_grid.py
tests/logic/test_mark.py
tictacai/__init__.py
tictacai/game/__init__.py
tictacai/game/engine.py
tictacai/game/engine_async.py
tictacai/game/players.py
tictacai/game/players_async.py
tictacai/game/renderers.py
tictacai/logic/__init__.py
tictacai/logic/exceptions.py
tictacai/logic/minimax.py
tictacai/logic/models.py
tictacai/logic/validators.py
tictacai-1.0.0.dist-info/LICENSE
tictacai-1.0.0.dist-info/METADATA
tictacai-1.0.0.dist-info/WHEEL
tictacai-1.0.0.dist-info/top_level.txt
tictacai-1.0.0.dist-info/RECORD
